{
  "swagger": "2.0",
  "info": {
    "title": "Todo API",
    "description": "API documentation for todo routes",
    "version": "1.0.0"
  },
  "host": "localhost:8000",
  "basePath": "/",
  "schemes": [
    "http"
  ],
  "paths": {
    "/": {
      "post": {
        "description": "",
        "responses": {
          "default": {
            "description": ""
          }
        }
      },
      "get": {
        "description": "",
        "responses": {
          "default": {
            "description": ""
          }
        }
      }
    },
    "/my-todos": {
      "get": {
        "description": "",
        "responses": {
          "default": {
            "description": ""
          }
        }
      }
    },
    "/{id}": {
      "patch": {
        "description": "",
        "responses": {
          "default": {
            "description": ""
          }
        }
      }
    }
  }
}